prawframe/__init__.py
prawframe/bot.py
prawframe/client.py
prawframe/client_connection.py
prawframe/common.py
prawframe/common_connection.py
prawframe/example.py
prawframe/obfuscation.py
prawframe/output.py
prawframe/pluginlib.py
prawframe/plugins.py
prawframe/schedules.py
prawframe/server.py
prawframe/server_connection.py
prawframe/sync.py
prawframe-0.0.1.dist-info/METADATA
prawframe-0.0.1.dist-info/RECORD
prawframe-0.0.1.dist-info/WHEEL
prawframe-0.0.1.dist-info/top_level.txt
