Metadata-Version: 2.1
Name: prawframe
Version: 0.0.1
Summary: prawframe is a small framework for running plugin-based reddit bots. prawframe supports scheduling plugins and includes a remote python console for modifying your bot's behavior while it runs.
Home-page: https://github.com/Wykleph/prawframe
Author: py-am-i
Author-email: duckpuncherirl@gmail.com
License: UNKNOWN
Platform: UNKNOWN
Classifier: Programming Language :: Python :: 3
Classifier: License :: OSI Approved :: MIT License
Classifier: Operating System :: OS Independent
